{
  "project": "AI_SYSTEM_BUILDER",
  "version": "0.8.0",
  "status": "in_flight",
  "tasks": [
    {
      "task_id": "TASK-001",
      "order": 1,
      "title": "Task A",
      "status": "completed",
      "dependencies": []
    },
    {
      "task_id": "TASK-003",
      "order": 2,
      "title": "Task C",
      "status": "completed",
      "dependencies": [
        "TASK-001",
        "TASK-004"
      ]
    },
    {
      "task_id": "TASK-004",
      "order": 3,
      "title": "Task D",
      "status": "completed",
      "dependencies": []
    },
    {
      "task_id": "TASK-005",
      "order": 4,
      "title": "Task E",
      "status": "in_progress",
      "dependencies": []
    },
    {
      "task_id": "TASK-006",
      "order": 5,
      "title": "Ordering verification task",
      "status": "completed",
      "dependencies": [
        "TASK-005"
      ]
    },
    {
      "task_id": "TASK-007",
      "order": 6,
      "title": "Dependency task for completion gating",
      "status": "completed",
      "dependencies": [
        "TASK-008"
      ]
    },
    {
      "task_id": "TASK-008",
      "order": 7,
      "title": "Blocked completion task",
      "status": "completed",
      "dependencies": []
    },
    {
      "task_id": "TASK-009",
      "order": 8,
      "title": "Predecessor",
      "status": "completed",
      "dependencies": []
    },
    {
      "task_id": "TASK-010",
      "order": 9,
      "title": "Successor",
      "status": "completed",
      "dependencies": [
        "TASK-009"
      ]
    }
  ]
}
