{
  "library_id": "M29_MVP_TRIAL_SCENARIO_COVERAGE_LIBRARY@v1",
  "version": "v1",
  "status": "mvp_trial_scenario_coverage_source",
  "scenarios": [
    {
      "scenario_id": "TRIALCOV-CLEANROOM-HVAC-NEW-INSTALL@v1",
      "version": "v1",
      "status": "mvp_trial_scenario_coverage_record",
      "display_name": "Cleanroom / HVAC new installation local review coverage",
      "domain": "cleanroom_hvac",
      "priority": "P0",
      "scenario_type": "local_review_flow",
      "lifecycle_event": "LE-NEW-INSTALLATION",
      "asset_archetype": null,
      "utility_system": null,
      "urs_dcf_required": true,
      "urs_dcf_route_ref": "DCF-CLEANROOM-URS@v1",
      "task_pool_refs": [
        "TP-MVP-CLEANROOM-HVAC-QUAL@v1"
      ],
      "profile_refs": [
        "PROF-MVP-CLEANROOM-HVAC@v1"
      ],
      "planning_basis_refs": [
        "M29_WAVE3_MVP_PLANNING_BASIS_LIBRARY@v1"
      ],
      "mapping_refs": [
        "MAP-MVP-PRESET-PF-CLEANROOM-TO-PROF-MVP-CLEANROOM-HVAC@v1"
      ],
      "document_refs": [
        "CCF",
        "VMP",
        "SIA",
        "URS",
        "RA_FMEA",
        "RTM",
        "DQ",
        "CP",
        "QP",
        "IQ_PROTOCOL_REPORT",
        "OQ_PROTOCOL_REPORT",
        "PQ_PROTOCOL_REPORT",
        "DEVIATION_INCIDENT_REPORT",
        "CAPA_CLOSURE_FORM",
        "VSR"
      ],
      "downstream_dependency_refs": [
        "M29_DOCUMENT_DEPENDENCY_CONTRACT_LIBRARY@v1",
        "M29_URS_DCF_INTAKE_CATALOG@v1"
      ],
      "standards_policy_refs": [
        "CITPOL-URS@v1",
        "CITPOL-DQ@v1",
        "CITPOL-IQ-PROTOCOL-REPORT@v1",
        "CITPOL-OQ-PROTOCOL-REPORT@v1",
        "CITPOL-PQ-PROTOCOL-REPORT@v1"
      ],
      "vendor_source_refs": [],
      "output_validation_expectations": [
        "Output validation remains required before any rendered sample can be treated as controlled local review evidence.",
        "Scenario coverage does not by itself render product-ready documents."
      ],
      "coverage_controls": [
        "Wave 7 trial scenario coverage records are local-review coverage records only.",
        "Trial scenario coverage records do not create UAT acceptance, release, deployment, productization, or SaaS readiness.",
        "Downstream document coverage remains dependent on URS, vendor/adopted records, task pools, profiles, mappings, standards/citation policy, and later validation."
      ],
      "local_review_only": true,
      "uat_acceptance_claimed": false,
      "customer_ready_release_claimed": false,
      "productization_claimed": false,
      "explicit_non_implementation_claims": [
        "does_not_create_uat_acceptance",
        "does_not_release_or_deploy_documents",
        "does_not_create_customer_ready_output",
        "does_not_create_qms_approval_records",
        "does_not_generate_documents",
        "does_not_productize_or_deploy_outputs"
      ]
    },
    {
      "scenario_id": "TRIALCOV-CLEANROOM-HVAC-PERIODIC-REQUAL@v1",
      "version": "v1",
      "status": "mvp_trial_scenario_coverage_record",
      "display_name": "Cleanroom / HVAC periodic requalification local review coverage",
      "domain": "cleanroom_hvac",
      "priority": "P0",
      "scenario_type": "local_review_flow",
      "lifecycle_event": "LE-PERIODIC-REQUALIFICATION",
      "asset_archetype": null,
      "utility_system": null,
      "urs_dcf_required": true,
      "urs_dcf_route_ref": "DCF-CLEANROOM-URS@v1",
      "task_pool_refs": [
        "TP-MVP-CLEANROOM-HVAC-QUAL@v1"
      ],
      "profile_refs": [
        "PROF-MVP-CLEANROOM-HVAC@v1"
      ],
      "planning_basis_refs": [
        "M29_WAVE3_MVP_PLANNING_BASIS_LIBRARY@v1"
      ],
      "mapping_refs": [
        "MAP-MVP-PRESET-PF-CLEANROOM-TO-PROF-MVP-CLEANROOM-HVAC@v1"
      ],
      "document_refs": [
        "CCF",
        "SIA",
        "URS",
        "RA_FMEA",
        "RTM",
        "OQ_PROTOCOL_REPORT",
        "PQ_PROTOCOL_REPORT",
        "DEVIATION_INCIDENT_REPORT",
        "CAPA_CLOSURE_FORM",
        "VSR"
      ],
      "downstream_dependency_refs": [
        "M29_DOCUMENT_DEPENDENCY_CONTRACT_LIBRARY@v1",
        "M29_URS_DCF_INTAKE_CATALOG@v1"
      ],
      "standards_policy_refs": [
        "CITPOL-URS@v1",
        "CITPOL-OQ-PROTOCOL-REPORT@v1",
        "CITPOL-PQ-PROTOCOL-REPORT@v1"
      ],
      "vendor_source_refs": [],
      "output_validation_expectations": [
        "Output validation remains required before any rendered sample can be treated as controlled local review evidence.",
        "Scenario coverage does not by itself render product-ready documents."
      ],
      "coverage_controls": [
        "Wave 7 trial scenario coverage records are local-review coverage records only.",
        "Trial scenario coverage records do not create UAT acceptance, release, deployment, productization, or SaaS readiness.",
        "Downstream document coverage remains dependent on URS, vendor/adopted records, task pools, profiles, mappings, standards/citation policy, and later validation."
      ],
      "local_review_only": true,
      "uat_acceptance_claimed": false,
      "customer_ready_release_claimed": false,
      "productization_claimed": false,
      "explicit_non_implementation_claims": [
        "does_not_create_uat_acceptance",
        "does_not_release_or_deploy_documents",
        "does_not_create_customer_ready_output",
        "does_not_create_qms_approval_records",
        "does_not_generate_documents",
        "does_not_productize_or_deploy_outputs"
      ]
    },
    {
      "scenario_id": "TRIALCOV-PE-NEW-INSTALL-TABCOMP@v1",
      "version": "v1",
      "status": "mvp_trial_scenario_coverage_record",
      "display_name": "Process equipment tablet compression new installation local review coverage",
      "domain": "process_equipment",
      "priority": "P0",
      "scenario_type": "local_review_flow",
      "lifecycle_event": "LE-NEW-INSTALLATION",
      "asset_archetype": "Tablet Compression Machine",
      "utility_system": null,
      "urs_dcf_required": true,
      "urs_dcf_route_ref": "DCF-PROCESS-EQUIPMENT-URS@v1",
      "task_pool_refs": [
        "TP-MVP-PE-TABCOMP-QUAL@v1"
      ],
      "profile_refs": [
        "PROF-MVP-PE-TABCOMP@v1"
      ],
      "planning_basis_refs": [
        "M29_WAVE3_MVP_PLANNING_BASIS_LIBRARY@v1"
      ],
      "mapping_refs": [
        "MAP-MVP-PRESET-PF-PROCESS-EQUIPMENT-TO-PROF-MVP-PE-TABCOMP@v1"
      ],
      "document_refs": [
        "CCF",
        "VMP",
        "SIA",
        "URS",
        "VENDOR_DOC_EXTRACTION_SOURCE",
        "RA_FMEA",
        "URS_DEVIATION_LIST",
        "RTM",
        "DQ",
        "CP",
        "QP",
        "IQ_PROTOCOL_REPORT",
        "OQ_PROTOCOL_REPORT",
        "PQ_PROTOCOL_REPORT",
        "DEVIATION_INCIDENT_REPORT",
        "CAPA_CLOSURE_FORM",
        "VSR"
      ],
      "downstream_dependency_refs": [
        "M29_DOCUMENT_DEPENDENCY_CONTRACT_LIBRARY@v1",
        "M29_URS_DCF_INTAKE_CATALOG@v1"
      ],
      "standards_policy_refs": [
        "CITPOL-URS@v1",
        "CITPOL-RA-FMEA@v1",
        "CITPOL-DQ@v1",
        "CITPOL-IQ-PROTOCOL-REPORT@v1",
        "CITPOL-OQ-PROTOCOL-REPORT@v1",
        "CITPOL-PQ-PROTOCOL-REPORT@v1"
      ],
      "vendor_source_refs": [
        "VENDOR_DOC_EXTRACTION_SOURCE"
      ],
      "output_validation_expectations": [
        "Output validation remains required before any rendered sample can be treated as controlled local review evidence.",
        "Scenario coverage does not by itself render product-ready documents."
      ],
      "coverage_controls": [
        "Wave 7 trial scenario coverage records are local-review coverage records only.",
        "Trial scenario coverage records do not create UAT acceptance, release, deployment, productization, or SaaS readiness.",
        "Downstream document coverage remains dependent on URS, vendor/adopted records, task pools, profiles, mappings, standards/citation policy, and later validation."
      ],
      "local_review_only": true,
      "uat_acceptance_claimed": false,
      "customer_ready_release_claimed": false,
      "productization_claimed": false,
      "explicit_non_implementation_claims": [
        "does_not_create_uat_acceptance",
        "does_not_release_or_deploy_documents",
        "does_not_create_customer_ready_output",
        "does_not_create_qms_approval_records",
        "does_not_generate_documents",
        "does_not_productize_or_deploy_outputs"
      ]
    },
    {
      "scenario_id": "TRIALCOV-PE-FAT-SAT-COMM-TABCOMP@v1",
      "version": "v1",
      "status": "mvp_trial_scenario_coverage_record",
      "display_name": "Process equipment FAT/SAT/commissioning route coverage",
      "domain": "process_equipment",
      "priority": "P0",
      "scenario_type": "fat_sat_commissioning_qualification_flow",
      "lifecycle_event": "LE-NEW-INSTALLATION",
      "asset_archetype": "Tablet Compression Machine",
      "utility_system": null,
      "urs_dcf_required": true,
      "urs_dcf_route_ref": "DCF-PROCESS-EQUIPMENT-URS@v1",
      "task_pool_refs": [
        "TP-MVP-PE-TABCOMP-QUAL@v1"
      ],
      "profile_refs": [
        "PROF-MVP-PE-TABCOMP@v1"
      ],
      "planning_basis_refs": [
        "M29_WAVE3_MVP_PLANNING_BASIS_LIBRARY@v1"
      ],
      "mapping_refs": [
        "MAP-MVP-PRESET-PF-PROCESS-EQUIPMENT-TO-PROF-MVP-PE-TABCOMP@v1"
      ],
      "document_refs": [
        "CCF",
        "SIA",
        "URS",
        "VENDOR_DOC_EXTRACTION_SOURCE",
        "DQ",
        "CP",
        "QP",
        "FAT_PROTOCOL_REPORT",
        "A0_CERTIFICATE",
        "CTOP",
        "A1_CERTIFICATE",
        "SAT_PROTOCOL_REPORT",
        "CR",
        "A2_CERTIFICATE",
        "IQ_PROTOCOL_REPORT",
        "OQ_PROTOCOL_REPORT",
        "DEVIATION_INCIDENT_REPORT",
        "VSR"
      ],
      "downstream_dependency_refs": [
        "M29_DOCUMENT_DEPENDENCY_CONTRACT_LIBRARY@v1",
        "M29_URS_DCF_INTAKE_CATALOG@v1"
      ],
      "standards_policy_refs": [
        "CITPOL-CP@v1",
        "CITPOL-FAT-PROTOCOL-REPORT@v1",
        "CITPOL-SAT-PROTOCOL-REPORT@v1",
        "CITPOL-CR@v1"
      ],
      "vendor_source_refs": [
        "VENDOR_DOC_EXTRACTION_SOURCE"
      ],
      "output_validation_expectations": [
        "Output validation remains required before any rendered sample can be treated as controlled local review evidence.",
        "Scenario coverage does not by itself render product-ready documents."
      ],
      "coverage_controls": [
        "Wave 7 trial scenario coverage records are local-review coverage records only.",
        "Trial scenario coverage records do not create UAT acceptance, release, deployment, productization, or SaaS readiness.",
        "Downstream document coverage remains dependent on URS, vendor/adopted records, task pools, profiles, mappings, standards/citation policy, and later validation."
      ],
      "local_review_only": true,
      "uat_acceptance_claimed": false,
      "customer_ready_release_claimed": false,
      "productization_claimed": false,
      "explicit_non_implementation_claims": [
        "does_not_create_uat_acceptance",
        "does_not_release_or_deploy_documents",
        "does_not_create_customer_ready_output",
        "does_not_create_qms_approval_records",
        "does_not_generate_documents",
        "does_not_productize_or_deploy_outputs"
      ]
    },
    {
      "scenario_id": "TRIALCOV-UTILITY-COMPRESSED-AIR@v1",
      "version": "v1",
      "status": "mvp_trial_scenario_coverage_record",
      "display_name": "Compressed Air System qualification local review coverage",
      "domain": "utilities",
      "priority": "P0",
      "scenario_type": "local_review_flow",
      "lifecycle_event": "LE-NEW-INSTALLATION",
      "asset_archetype": null,
      "utility_system": "Compressed Air System",
      "urs_dcf_required": true,
      "urs_dcf_route_ref": "DCF-UTILITIES-URS@v1",
      "task_pool_refs": [
        "TP-MVP-UTIL-COMPRESSED-AIR-QUAL@v1"
      ],
      "profile_refs": [
        "PROF-MVP-UTIL-COMPRESSED-AIR@v1"
      ],
      "planning_basis_refs": [
        "M29_WAVE3_MVP_PLANNING_BASIS_LIBRARY@v1"
      ],
      "mapping_refs": [
        "MAP-MVP-PRESET-PF-UTILITIES-TO-PROF-MVP-UTIL-COMPRESSED-AIR@v1"
      ],
      "document_refs": [
        "CCF",
        "SIA",
        "URS",
        "RA_FMEA",
        "RTM",
        "DQ",
        "CP",
        "QP",
        "CTOP",
        "A1_CERTIFICATE",
        "CR",
        "A2_CERTIFICATE",
        "IQ_PROTOCOL_REPORT",
        "OQ_PROTOCOL_REPORT",
        "PQ_PROTOCOL_REPORT",
        "DEVIATION_INCIDENT_REPORT",
        "CAPA_CLOSURE_FORM",
        "VSR"
      ],
      "downstream_dependency_refs": [
        "M29_DOCUMENT_DEPENDENCY_CONTRACT_LIBRARY@v1",
        "M29_URS_DCF_INTAKE_CATALOG@v1"
      ],
      "standards_policy_refs": [
        "CITPOL-URS@v1",
        "CITPOL-IQ-PROTOCOL-REPORT@v1",
        "CITPOL-OQ-PROTOCOL-REPORT@v1",
        "CITPOL-PQ-PROTOCOL-REPORT@v1"
      ],
      "vendor_source_refs": [],
      "output_validation_expectations": [
        "Output validation remains required before any rendered sample can be treated as controlled local review evidence.",
        "Scenario coverage does not by itself render product-ready documents."
      ],
      "coverage_controls": [
        "Wave 7 trial scenario coverage records are local-review coverage records only.",
        "Trial scenario coverage records do not create UAT acceptance, release, deployment, productization, or SaaS readiness.",
        "Downstream document coverage remains dependent on URS, vendor/adopted records, task pools, profiles, mappings, standards/citation policy, and later validation."
      ],
      "local_review_only": true,
      "uat_acceptance_claimed": false,
      "customer_ready_release_claimed": false,
      "productization_claimed": false,
      "explicit_non_implementation_claims": [
        "does_not_create_uat_acceptance",
        "does_not_release_or_deploy_documents",
        "does_not_create_customer_ready_output",
        "does_not_create_qms_approval_records",
        "does_not_generate_documents",
        "does_not_productize_or_deploy_outputs"
      ]
    },
    {
      "scenario_id": "TRIALCOV-UTILITY-PURIFIED-REFINED-WATER@v1",
      "version": "v1",
      "status": "mvp_trial_scenario_coverage_record",
      "display_name": "Purified / Refined Water System qualification local review coverage",
      "domain": "utilities",
      "priority": "P0",
      "scenario_type": "local_review_flow",
      "lifecycle_event": "LE-NEW-INSTALLATION",
      "asset_archetype": null,
      "utility_system": "Purified / Refined Water System",
      "urs_dcf_required": true,
      "urs_dcf_route_ref": "DCF-UTILITIES-URS@v1",
      "task_pool_refs": [
        "TP-MVP-UTIL-PURIFIED-WATER-QUAL@v1"
      ],
      "profile_refs": [
        "PROF-MVP-UTIL-PURIFIED-WATER@v1"
      ],
      "planning_basis_refs": [
        "M29_WAVE3_MVP_PLANNING_BASIS_LIBRARY@v1"
      ],
      "mapping_refs": [
        "MAP-MVP-PRESET-PF-UTILITIES-TO-PROF-MVP-UTIL-PURIFIED-WATER@v1"
      ],
      "document_refs": [
        "CCF",
        "SIA",
        "URS",
        "RA_FMEA",
        "RTM",
        "DQ",
        "CP",
        "QP",
        "IQ_PROTOCOL_REPORT",
        "OQ_PROTOCOL_REPORT",
        "PQ_PROTOCOL_REPORT",
        "DEVIATION_INCIDENT_REPORT",
        "CAPA_CLOSURE_FORM",
        "VSR"
      ],
      "downstream_dependency_refs": [
        "M29_DOCUMENT_DEPENDENCY_CONTRACT_LIBRARY@v1",
        "M29_URS_DCF_INTAKE_CATALOG@v1"
      ],
      "standards_policy_refs": [
        "CITPOL-QP@v1"
      ],
      "vendor_source_refs": [],
      "output_validation_expectations": [
        "Output validation remains required before any rendered sample can be treated as controlled local review evidence.",
        "Scenario coverage does not by itself render product-ready documents."
      ],
      "coverage_controls": [
        "Wave 7 trial scenario coverage records are local-review coverage records only.",
        "Trial scenario coverage records do not create UAT acceptance, release, deployment, productization, or SaaS readiness.",
        "Downstream document coverage remains dependent on URS, vendor/adopted records, task pools, profiles, mappings, standards/citation policy, and later validation."
      ],
      "local_review_only": true,
      "uat_acceptance_claimed": false,
      "customer_ready_release_claimed": false,
      "productization_claimed": false,
      "explicit_non_implementation_claims": [
        "does_not_create_uat_acceptance",
        "does_not_release_or_deploy_documents",
        "does_not_create_customer_ready_output",
        "does_not_create_qms_approval_records",
        "does_not_generate_documents",
        "does_not_productize_or_deploy_outputs"
      ]
    },
    {
      "scenario_id": "TRIALCOV-UTILITY-HVAC-SYSTEM@v1",
      "version": "v1",
      "status": "mvp_trial_scenario_coverage_record",
      "display_name": "HVAC System utility qualification local review coverage",
      "domain": "utilities",
      "priority": "P0",
      "scenario_type": "local_review_flow",
      "lifecycle_event": "LE-NEW-INSTALLATION",
      "asset_archetype": null,
      "utility_system": "HVAC System",
      "urs_dcf_required": true,
      "urs_dcf_route_ref": "DCF-UTILITIES-URS@v1",
      "task_pool_refs": [
        "TP-MVP-UTIL-HVAC-QUAL@v1"
      ],
      "profile_refs": [
        "PROF-MVP-UTIL-HVAC@v1"
      ],
      "planning_basis_refs": [
        "M29_WAVE3_MVP_PLANNING_BASIS_LIBRARY@v1"
      ],
      "mapping_refs": [
        "MAP-MVP-PRESET-PF-UTILITIES-TO-PROF-MVP-UTIL-HVAC@v1"
      ],
      "document_refs": [
        "CCF",
        "SIA",
        "URS",
        "RA_FMEA",
        "RTM",
        "DQ",
        "CP",
        "QP",
        "IQ_PROTOCOL_REPORT",
        "OQ_PROTOCOL_REPORT",
        "PQ_PROTOCOL_REPORT",
        "DEVIATION_INCIDENT_REPORT",
        "CAPA_CLOSURE_FORM",
        "VSR"
      ],
      "downstream_dependency_refs": [
        "M29_DOCUMENT_DEPENDENCY_CONTRACT_LIBRARY@v1",
        "M29_URS_DCF_INTAKE_CATALOG@v1"
      ],
      "standards_policy_refs": [
        "CITPOL-QP@v1"
      ],
      "vendor_source_refs": [],
      "output_validation_expectations": [
        "Output validation remains required before any rendered sample can be treated as controlled local review evidence.",
        "Scenario coverage does not by itself render product-ready documents."
      ],
      "coverage_controls": [
        "Wave 7 trial scenario coverage records are local-review coverage records only.",
        "Trial scenario coverage records do not create UAT acceptance, release, deployment, productization, or SaaS readiness.",
        "Downstream document coverage remains dependent on URS, vendor/adopted records, task pools, profiles, mappings, standards/citation policy, and later validation."
      ],
      "local_review_only": true,
      "uat_acceptance_claimed": false,
      "customer_ready_release_claimed": false,
      "productization_claimed": false,
      "explicit_non_implementation_claims": [
        "does_not_create_uat_acceptance",
        "does_not_release_or_deploy_documents",
        "does_not_create_customer_ready_output",
        "does_not_create_qms_approval_records",
        "does_not_generate_documents",
        "does_not_productize_or_deploy_outputs"
      ]
    },
    {
      "scenario_id": "TRIALCOV-UTILITY-CHILLED-WATER@v1",
      "version": "v1",
      "status": "mvp_trial_scenario_coverage_record",
      "display_name": "Chilled Water System qualification local review coverage",
      "domain": "utilities",
      "priority": "P0",
      "scenario_type": "local_review_flow",
      "lifecycle_event": "LE-NEW-INSTALLATION",
      "asset_archetype": null,
      "utility_system": "Chilled Water System",
      "urs_dcf_required": true,
      "urs_dcf_route_ref": "DCF-UTILITIES-URS@v1",
      "task_pool_refs": [
        "TP-MVP-UTIL-CHILLED-WATER-QUAL@v1"
      ],
      "profile_refs": [
        "PROF-MVP-UTIL-CHILLED-WATER@v1"
      ],
      "planning_basis_refs": [
        "M29_WAVE3_MVP_PLANNING_BASIS_LIBRARY@v1"
      ],
      "mapping_refs": [
        "MAP-MVP-PRESET-PF-UTILITIES-TO-PROF-MVP-UTIL-CHILLED-WATER@v1"
      ],
      "document_refs": [
        "CCF",
        "SIA",
        "URS",
        "RA_FMEA",
        "RTM",
        "DQ",
        "CP",
        "QP",
        "IQ_PROTOCOL_REPORT",
        "OQ_PROTOCOL_REPORT",
        "PQ_PROTOCOL_REPORT",
        "DEVIATION_INCIDENT_REPORT",
        "CAPA_CLOSURE_FORM",
        "VSR"
      ],
      "downstream_dependency_refs": [
        "M29_DOCUMENT_DEPENDENCY_CONTRACT_LIBRARY@v1",
        "M29_URS_DCF_INTAKE_CATALOG@v1"
      ],
      "standards_policy_refs": [
        "CITPOL-QP@v1"
      ],
      "vendor_source_refs": [],
      "output_validation_expectations": [
        "Output validation remains required before any rendered sample can be treated as controlled local review evidence.",
        "Scenario coverage does not by itself render product-ready documents."
      ],
      "coverage_controls": [
        "Wave 7 trial scenario coverage records are local-review coverage records only.",
        "Trial scenario coverage records do not create UAT acceptance, release, deployment, productization, or SaaS readiness.",
        "Downstream document coverage remains dependent on URS, vendor/adopted records, task pools, profiles, mappings, standards/citation policy, and later validation."
      ],
      "local_review_only": true,
      "uat_acceptance_claimed": false,
      "customer_ready_release_claimed": false,
      "productization_claimed": false,
      "explicit_non_implementation_claims": [
        "does_not_create_uat_acceptance",
        "does_not_release_or_deploy_documents",
        "does_not_create_customer_ready_output",
        "does_not_create_qms_approval_records",
        "does_not_generate_documents",
        "does_not_productize_or_deploy_outputs"
      ]
    },
    {
      "scenario_id": "TRIALCOV-CSV-COMPUTERIZED-SYSTEM@v1",
      "version": "v1",
      "status": "mvp_trial_scenario_coverage_record",
      "display_name": "Computerized system validation local review coverage",
      "domain": "csv",
      "priority": "P0",
      "scenario_type": "local_review_flow",
      "lifecycle_event": "LE-NEW-INSTALLATION",
      "asset_archetype": null,
      "utility_system": null,
      "urs_dcf_required": true,
      "urs_dcf_route_ref": "DCF-COMPUTERIZED-SYSTEMS-URS@v1",
      "task_pool_refs": [
        "TP-MVP-CSV-COMPUTERIZED-SYSTEM-VALIDATION@v1"
      ],
      "profile_refs": [
        "PROF-MVP-CSV-COMPUTERIZED-SYSTEM@v1"
      ],
      "planning_basis_refs": [
        "M29_WAVE3_MVP_PLANNING_BASIS_LIBRARY@v1"
      ],
      "mapping_refs": [
        "MAP-MVP-PRESET-PF-COMPUTERIZED-SYSTEMS-TO-PROF-MVP-CSV@v1"
      ],
      "document_refs": [
        "CCF",
        "VMP",
        "SIA",
        "URS",
        "VENDOR_DOC_EXTRACTION_SOURCE",
        "RA_FMEA",
        "RTM",
        "DQ",
        "QP",
        "DEVIATION_INCIDENT_REPORT",
        "CAPA_CLOSURE_FORM",
        "VSR"
      ],
      "downstream_dependency_refs": [
        "M29_DOCUMENT_DEPENDENCY_CONTRACT_LIBRARY@v1",
        "M29_URS_DCF_INTAKE_CATALOG@v1"
      ],
      "standards_policy_refs": [
        "CITPOL-URS@v1",
        "CITPOL-RTM@v1",
        "CITPOL-VSR@v1"
      ],
      "vendor_source_refs": [
        "VENDOR_DOC_EXTRACTION_SOURCE"
      ],
      "output_validation_expectations": [
        "Output validation remains required before any rendered sample can be treated as controlled local review evidence.",
        "Scenario coverage does not by itself render product-ready documents."
      ],
      "coverage_controls": [
        "Wave 7 trial scenario coverage records are local-review coverage records only.",
        "Trial scenario coverage records do not create UAT acceptance, release, deployment, productization, or SaaS readiness.",
        "Downstream document coverage remains dependent on URS, vendor/adopted records, task pools, profiles, mappings, standards/citation policy, and later validation."
      ],
      "local_review_only": true,
      "uat_acceptance_claimed": false,
      "customer_ready_release_claimed": false,
      "productization_claimed": false,
      "explicit_non_implementation_claims": [
        "does_not_create_uat_acceptance",
        "does_not_release_or_deploy_documents",
        "does_not_create_customer_ready_output",
        "does_not_create_qms_approval_records",
        "does_not_generate_documents",
        "does_not_productize_or_deploy_outputs"
      ]
    },
    {
      "scenario_id": "TRIALCOV-QC-LAB-EQUIPMENT-CAL-CSV-LINK@v1",
      "version": "v1",
      "status": "mvp_trial_scenario_coverage_record",
      "display_name": "QC lab equipment calibration and CSV-linkage local review coverage",
      "domain": "qc_lab_equipment",
      "priority": "P0",
      "scenario_type": "local_review_flow",
      "lifecycle_event": "LE-NEW-INSTALLATION",
      "asset_archetype": null,
      "utility_system": null,
      "urs_dcf_required": true,
      "urs_dcf_route_ref": "DCF-PROCESS-EQUIPMENT-URS@v1",
      "task_pool_refs": [
        "TP-MVP-QCLAB-EQUIPMENT-QUAL@v1"
      ],
      "profile_refs": [
        "PROF-MVP-QC-LAB-EQUIPMENT@v1"
      ],
      "planning_basis_refs": [
        "M29_WAVE3_MVP_PLANNING_BASIS_LIBRARY@v1"
      ],
      "mapping_refs": [
        "MAP-MVP-PRESET-PF-QC-LAB-EQUIPMENT-TO-PROF-MVP-QCLAB@v1"
      ],
      "document_refs": [
        "CCF",
        "SIA",
        "URS",
        "VENDOR_DOC_EXTRACTION_SOURCE",
        "RA_FMEA",
        "RTM",
        "DQ",
        "IQ_PROTOCOL_REPORT",
        "OQ_PROTOCOL_REPORT",
        "PQ_PROTOCOL_REPORT",
        "DEVIATION_INCIDENT_REPORT",
        "CAPA_CLOSURE_FORM",
        "VSR"
      ],
      "downstream_dependency_refs": [
        "M29_DOCUMENT_DEPENDENCY_CONTRACT_LIBRARY@v1",
        "M29_URS_DCF_INTAKE_CATALOG@v1"
      ],
      "standards_policy_refs": [
        "CITPOL-URS@v1",
        "CITPOL-IQ-PROTOCOL-REPORT@v1",
        "CITPOL-OQ-PROTOCOL-REPORT@v1",
        "CITPOL-PQ-PROTOCOL-REPORT@v1"
      ],
      "vendor_source_refs": [
        "VENDOR_DOC_EXTRACTION_SOURCE"
      ],
      "output_validation_expectations": [
        "Output validation remains required before any rendered sample can be treated as controlled local review evidence.",
        "Scenario coverage does not by itself render product-ready documents."
      ],
      "coverage_controls": [
        "Wave 7 trial scenario coverage records are local-review coverage records only.",
        "Trial scenario coverage records do not create UAT acceptance, release, deployment, productization, or SaaS readiness.",
        "Downstream document coverage remains dependent on URS, vendor/adopted records, task pools, profiles, mappings, standards/citation policy, and later validation."
      ],
      "local_review_only": true,
      "uat_acceptance_claimed": false,
      "customer_ready_release_claimed": false,
      "productization_claimed": false,
      "explicit_non_implementation_claims": [
        "does_not_create_uat_acceptance",
        "does_not_release_or_deploy_documents",
        "does_not_create_customer_ready_output",
        "does_not_create_qms_approval_records",
        "does_not_generate_documents",
        "does_not_productize_or_deploy_outputs"
      ]
    },
    {
      "scenario_id": "TRIALCOV-DECOMMISSIONING-ROUTE@v1",
      "version": "v1",
      "status": "mvp_trial_scenario_coverage_record",
      "display_name": "MVP decommissioning lifecycle route coverage",
      "domain": "decommissioning",
      "priority": "P0",
      "scenario_type": "local_review_flow",
      "lifecycle_event": "LE-DECOMMISSIONING",
      "asset_archetype": null,
      "utility_system": null,
      "urs_dcf_required": false,
      "urs_dcf_route_ref": null,
      "task_pool_refs": [
        "TP-MVP-DECOMMISSIONING-ROUTE@v1"
      ],
      "profile_refs": [
        "PROF-MVP-DECOMMISSIONING@v1"
      ],
      "planning_basis_refs": [
        "M29_WAVE3_MVP_PLANNING_BASIS_LIBRARY@v1"
      ],
      "mapping_refs": [
        "MAP-MVP-DECOMMISSIONING-ROUTE@v1"
      ],
      "document_refs": [
        "CCF",
        "SIA",
        "RA_FMEA",
        "RTM",
        "DEVIATION_INCIDENT_REPORT",
        "CAPA_CLOSURE_FORM",
        "VSR",
        "DECOMMISSIONING_DOCUMENT_SET"
      ],
      "downstream_dependency_refs": [
        "M29_DOCUMENT_DEPENDENCY_CONTRACT_LIBRARY@v1",
        "M29_URS_DCF_INTAKE_CATALOG@v1"
      ],
      "standards_policy_refs": [
        "CITPOL-DECOMMISSIONING-DOCUMENT-SET@v1"
      ],
      "vendor_source_refs": [],
      "output_validation_expectations": [
        "Output validation remains required before any rendered sample can be treated as controlled local review evidence.",
        "Scenario coverage does not by itself render product-ready documents."
      ],
      "coverage_controls": [
        "Wave 7 trial scenario coverage records are local-review coverage records only.",
        "Trial scenario coverage records do not create UAT acceptance, release, deployment, productization, or SaaS readiness.",
        "Downstream document coverage remains dependent on URS, vendor/adopted records, task pools, profiles, mappings, standards/citation policy, and later validation.",
        "Decommissioning document set remains an owner-finalized route; this coverage record does not invent final document content."
      ],
      "local_review_only": true,
      "uat_acceptance_claimed": false,
      "customer_ready_release_claimed": false,
      "productization_claimed": false,
      "explicit_non_implementation_claims": [
        "does_not_create_uat_acceptance",
        "does_not_release_or_deploy_documents",
        "does_not_create_customer_ready_output",
        "does_not_create_qms_approval_records",
        "does_not_generate_documents",
        "does_not_productize_or_deploy_outputs"
      ]
    },
    {
      "scenario_id": "TRIALCOV-MANUAL-FALLBACK-UNSUPPORTED-SCOPE@v1",
      "version": "v1",
      "status": "mvp_trial_scenario_coverage_record",
      "display_name": "Manual fallback unsupported-scope local review coverage",
      "domain": "manual_fallback",
      "priority": "P0",
      "scenario_type": "manual_fallback_safety_route",
      "lifecycle_event": "LE-MIXED-OR-OTHER",
      "asset_archetype": null,
      "utility_system": null,
      "urs_dcf_required": false,
      "urs_dcf_route_ref": null,
      "task_pool_refs": [
        "TP-MVP-MANUAL-FALLBACK-ROUTE@v1"
      ],
      "profile_refs": [
        "PROF-MVP-MANUAL-FALLBACK@v1"
      ],
      "planning_basis_refs": [
        "M29_WAVE3_MVP_PLANNING_BASIS_LIBRARY@v1"
      ],
      "mapping_refs": [
        "MAP-MVP-MANUAL-FALLBACK-ROUTE@v1"
      ],
      "document_refs": [
        "CCF",
        "SIA",
        "DEVIATION_INCIDENT_REPORT",
        "CAPA_CLOSURE_FORM",
        "VSR"
      ],
      "downstream_dependency_refs": [
        "M29_DOCUMENT_DEPENDENCY_CONTRACT_LIBRARY@v1",
        "M29_URS_DCF_INTAKE_CATALOG@v1"
      ],
      "standards_policy_refs": [
        "CITPOL-CCF@v1"
      ],
      "vendor_source_refs": [],
      "output_validation_expectations": [
        "Output validation remains required before any rendered sample can be treated as controlled local review evidence.",
        "Scenario coverage does not by itself render product-ready documents."
      ],
      "coverage_controls": [
        "Wave 7 trial scenario coverage records are local-review coverage records only.",
        "Trial scenario coverage records do not create UAT acceptance, release, deployment, productization, or SaaS readiness.",
        "Downstream document coverage remains dependent on URS, vendor/adopted records, task pools, profiles, mappings, standards/citation policy, and later validation.",
        "Manual fallback is a safety route only and must not substitute for missing mature source-library coverage."
      ],
      "local_review_only": true,
      "uat_acceptance_claimed": false,
      "customer_ready_release_claimed": false,
      "productization_claimed": false,
      "explicit_non_implementation_claims": [
        "does_not_create_uat_acceptance",
        "does_not_release_or_deploy_documents",
        "does_not_create_customer_ready_output",
        "does_not_create_qms_approval_records",
        "does_not_generate_documents",
        "does_not_productize_or_deploy_outputs"
      ]
    }
  ],
  "library_controls": [
    "Wave 7 expands local trial scenario coverage only.",
    "Trial scenario coverage proves coverage relationships; it does not create UAT acceptance or customer-ready output.",
    "Rendered trial samples, when generated, remain local-review-only and require output validation.",
    "Post-remediation control still requires a full repository index before returning to UAT or further build continuation."
  ],
  "explicit_non_implementation_claims": [
    "does_not_create_uat_acceptance",
    "does_not_release_or_deploy_documents",
    "does_not_create_customer_ready_output",
    "does_not_create_qms_approval_records",
    "does_not_generate_documents",
    "does_not_productize_or_deploy_outputs"
  ]
}
